osrf_pycommon/__init__.py
osrf_pycommon/terminal_utils.py
osrf_pycommon/cli_utils/__init__.py
osrf_pycommon/cli_utils/common.py
osrf_pycommon/cli_utils/verb_pattern.py
osrf_pycommon/process_utils/__init__.py
osrf_pycommon/process_utils/async_execute_process.py
osrf_pycommon/process_utils/execute_process_nopty.py
osrf_pycommon/process_utils/execute_process_pty.py
osrf_pycommon/process_utils/get_loop_impl.py
osrf_pycommon/process_utils/impl.py
osrf_pycommon/process_utils/async_execute_process_asyncio/__init__.py
osrf_pycommon/process_utils/async_execute_process_asyncio/impl.py
osrf_pycommon/terminal_color/__init__.py
osrf_pycommon/terminal_color/ansi_re.py
osrf_pycommon/terminal_color/impl.py
osrf_pycommon/terminal_color/windows.py
osrf_pycommon-2.0.2.data/data/share/ament_index/resource_index/packages/osrf_pycommon
osrf_pycommon-2.0.2.data/data/share/osrf_pycommon/package.xml
osrf_pycommon-2.0.2.dist-info/DESCRIPTION.rst
osrf_pycommon-2.0.2.dist-info/METADATA
osrf_pycommon-2.0.2.dist-info/RECORD
osrf_pycommon-2.0.2.dist-info/WHEEL
osrf_pycommon-2.0.2.dist-info/metadata.json
osrf_pycommon-2.0.2.dist-info/top_level.txt
osrf_pycommon-2.0.2.dist-info/zip-safe
